{
  "1049651": {
    "imo": "1049651",
    "name": "BOUKRAA-I",
    "flag": "St Vincent & Grenadines",
    "ship_type": "Tug",
    "length_overall_m": "-",
    "beam_m": "-",
    "deadweight_t": "-",
    "gross_tonnage": "301",
    "year_of_build": "2025"
  },
  "6417499": {
    "imo": "6417499",
    "name": "NAVE SANTA MARIA",
    "flag": "Panama",
    "ship_type": "Offshore Support Vessel",
    "length_overall_m": "35.72",
    "beam_m": "7.09",
    "deadweight_t": "165",
    "gross_tonnage": "194",
    "year_of_build": "1964"
  },
  "7325461": {
    "imo": "7325461",
    "vessel_name": "DURA BULK",
    "flag": "Panama",
    "ship_type": "General Cargo Ship",
    "length_overall_m": "88.85",
    "beam_m": "13.28",
    "deadweight_t": "3007",
    "gross_tonnage": "2239",
    "year_of_build": "1973"
  },
  "9128013": {
    "imo": "9128013",
    "name": "RIGHT STEP",
    "flag": "Antigua & Barbuda",
    "ship_type": "General Cargo Ship",
    "length_overall_m": "100.70",
    "beam_m": "16.00",
    "deadweight_t": "5200",
    "gross_tonnage": "3796",
    "year_of_build": "1996"
  },
  "9212448": {
    "imo": "9212448",
    "name": "STORM I",
    "flag": "Panama",
    "ship_type": "General Cargo Ship",
    "length_overall_m": "100.58",
    "beam_m": "18.80",
    "deadweight_t": "6962",
    "gross_tonnage": "4450",
    "year_of_build": "1999"
  },
  "9234276": {
    "imo": "9234276",
    "name": "VICTORIABORG",
    "flag": "Netherlands",
    "ship_type": "General Cargo Ship",
    "length_overall_m": "132.23",
    "beam_m": "15.87",
    "deadweight_t": "9826",
    "gross_tonnage": "6361",
    "year_of_build": "2001"
  },
  "9310197": {
    "imo": "9310197",
    "name": "TINGIS",
    "flag": "Morocco",
    "ship_type": "Chemical/Oil Products Tanker",
    "length_overall_m": "119.10",
    "beam_m": "16.93",
    "deadweight_t": "6937",
    "gross_tonnage": "4471",
    "year_of_build": "2005"
  },
  "9313503": {
    "imo": "9313503",
    "name": "FASSA",
    "flag": "Cayman Islands",
    "ship_type": "Bulk Carrier",
    "length_overall_m": "189.99",
    "beam_m": "32.26",
    "deadweight_t": "55447",
    "gross_tonnage": "30936",
    "year_of_build": "2006"
  },
  "9364150": {
    "imo": "9364150",
    "name": "SINE BRES",
    "flag": "Antigua & Barbuda",
    "ship_type": "General Cargo Ship",
    "length_overall_m": "87.90",
    "beam_m": "12.60",
    "deadweight_t": "3750",
    "gross_tonnage": "2658",
    "year_of_build": "2006"
  },
  "9427079": {
    "imo": "9427079",
    "name": "BBC GREENLAND",
    "flag": "Antigua & Barbuda",
    "ship_type": "General Cargo Ship",
    "length_overall_m": "119.81",
    "beam_m": "20.53",
    "deadweight_t": "7536",
    "gross_tonnage": "7002",
    "year_of_build": "2007"
  },
  "9428889": {
    "imo": "9428889",
    "name": "BOMAR MERCURY",
    "flag": "Malta",
    "ship_type": "Chemical/Oil Products Tanker",
    "length_overall_m": "119.60",
    "beam_m": "16.90",
    "deadweight_t": "7003",
    "gross_tonnage": "4808",
    "year_of_build": "2008"
  },
  "9462093": {
    "imo": "9462093",
    "name": "PS OUFELLA",
    "flag": "Morocco",
    "ship_type": "Oil Products Tanker",
    "length_overall_m": "64.44",
    "beam_m": "12.00",
    "deadweight_t": "1792",
    "gross_tonnage": "1055",
    "year_of_build": "2007"
  },
  "9501655": {
    "imo": "9501655",
    "name": "BBC BELEM",
    "flag": "Antigua & Barbuda",
    "ship_type": "General Cargo Ship",
    "length_overall_m": "128.97",
    "beam_m": "16.71",
    "deadweight_t": "8129",
    "gross_tonnage": "6310",
    "year_of_build": "2012"
  },
  "9518880": {
    "imo": "9518880",
    "name": "ARGAN",
    "flag": "Morocco",
    "ship_type": "Chemical/Oil Products Tanker",
    "length_overall_m": "99.87",
    "beam_m": "18.24",
    "deadweight_t": "7374",
    "gross_tonnage": "4776",
    "year_of_build": "2011"
  },
  "9520132": {
    "imo": "9520132",
    "vessel_name": "BWEK MALTA",
    "flag": "Singapore",
    "ship_type": "LPG Tanker",
    "length_overall_m": "119.95",
    "beam_m": "19.00",
    "deadweight_t": "9011",
    "gross_tonnage": "7222",
    "year_of_build": "2011"
  },
  "9544346": {
    "imo": "9544346",
    "name": "MT MED BLUE JAY",
    "flag": "Malta",
    "ship_type": "Chemical/Oil Products Tanker",
    "length_overall_m": "115.97",
    "beam_m": "17.20",
    "deadweight_t": "8231",
    "gross_tonnage": "5633",
    "year_of_build": "2021"
  },
  "9611802": {
    "imo": "9611802",
    "vessel_name": "ASTRA CENTAURUS",
    "flag": "Marshall Islands",
    "ship_type": "Bulk Carrier",
    "length_overall_m": "196.00",
    "beam_m": "32.26",
    "deadweight_t": "58518",
    "gross_tonnage": "34837",
    "year_of_build": "2012"
  },
  "9813046": {
    "imo": "9813046",
    "name": "DH BLOSSOMING",
    "flag": "Singapore",
    "ship_type": "Chemical/Oil Products Tanker",
    "length_overall_m": "119.00",
    "beam_m": "18.00",
    "deadweight_t": "8703",
    "gross_tonnage": "6052",
    "year_of_build": "2018"
  },
  "9835185": {
    "imo": "9835185",
    "name": "VIVIT FORNAX",
    "flag": "Liberia",
    "ship_type": "LPG Tanker",
    "length_overall_m": "228.40",
    "beam_m": "36.60",
    "deadweight_t": "54406",
    "gross_tonnage": "49552",
    "year_of_build": "2019"
  },
  "9841421": {
    "imo": "9841421",
    "name": "DING HENG 23",
    "flag": "Hong Kong",
    "ship_type": "Chemical/Oil Products Tanker",
    "length_overall_m": "120.00",
    "beam_m": "19.00",
    "deadweight_t": "9014",
    "gross_tonnage": "6205",
    "year_of_build": "2024"
  },
  "9933913": {
    "imo": "9933913",
    "name": "CHALLAH",
    "flag": "Morocco",
    "ship_type": "Oil Products Tanker",
    "length_overall_m": "117.53",
    "beam_m": "19.50",
    "deadweight_t": "9137",
    "gross_tonnage": "6822",
    "year_of_build": "2022"
  }
}